Metadata-Version: 2.4
Name: mcp-server-logseq
Version: 0.0.3
Summary: An MCP server for LogSeq API
Project-URL: homepage, https://github.com/dailydaniel/logseq-mcp
Project-URL: repository, https://github.com/dailydaniel/logseq-mcp
Project-URL: issues, https://github.com/dailydaniel/logseq-mcp/issues
Author-email: Daniel Zholkovsky <daniel@zholkovsky.com>
Maintainer-email: Daniel Zholkovsky <daniel@zholkovsky.com>
License: MIT
License-File: LICENSE
Keywords: automation,http,llm,mcp
Classifier: Development Status :: 4 - Beta
Classifier: Intended Audience :: Developers
Classifier: License :: OSI Approved :: MIT License
Classifier: Programming Language :: Python :: 3
Classifier: Programming Language :: Python :: 3.10
Requires-Python: >=3.10
Requires-Dist: mcp>=1.2.1
Requires-Dist: pydantic>=2.10.2
Requires-Dist: python-dotenv>=1.0.1
Requires-Dist: requests>=2.32.3
